<GVDispenserWidget xmlns="runtime-namespace:Game">
  <BevelledRectangleWidget Size="614, 382" BevelSize="3"/>
  <LabelWidget CanvasWidget.Position="12, 14" Name="DispenserLabel" Text="[GVDispenserWidget:1]" Color="255, 255, 255, 192"/>
  <LabelWidget CanvasWidget.Position="306, 14" Name="InventoryLabel" Text="[GVDispenserWidget:2]" Color="255, 255, 255, 192"/>
  <GridPanelWidget CanvasWidget.Position="12, 52" Name="DispenserGrid" ColumnsCount="4" RowsCount="2"/>
  <GridPanelWidget CanvasWidget.Position="306, 52" Name="InventoryGrid" ColumnsCount="4" RowsCount="4"/>
  <CanvasWidget CanvasWidget.Position="12, 200" Size="288, 140">
    <StackPanelWidget Direction="Vertical" HorizontalAlignment="Center" VerticalAlignment="Center">
      <BevelledButtonWidget Name="DispenseButton" Text="[GVDispenserWidget:3]" Style="{Styles/ButtonStyle_160x60}"/>
      <BevelledButtonWidget Name="ShootButton" Text="[GVDispenserWidget:4]" Style="{Styles/ButtonStyle_160x60}"/>
      <CheckboxWidget Name="AcceptsDropsBox" Text="[GVDispenserWidget:5]"/>
    </StackPanelWidget>
  </CanvasWidget>
</GVDispenserWidget>
